{
  "listings": [
    {
      "destination_id": "LON",
      "origin_id": "BAK",
      "feed_description": "???????? ?????? ?? ??????????? Baku - London",
      "flight_price": "194.20 USD",
      "origin_name": "Baku",
      "destination_name": "London",
      "feed_start_date": "20.10.2025",
      "final_url": "https://www.azal.az/az?utm_source=sheet_cataloue&from=BAK&to=LON",
      "image_url": "https://raw.githubusercontent.com/subhanahmet/testflight/main/images/no_price/BAK-LON.jpg?ts=519746",
      "github_image_urls": "https://raw.githubusercontent.com/subhanahmet/testflight/main/images/no_price/BAK-LON.jpg",
      "feed_type": "Local Feed",
      "or_cirty": "",
      "dep_city": "",
      "flight_description": "",
      "rounded_price": 194
    },
    {
      "destination_id": "AYT",
      "origin_id": "BAK",
      "feed_description": "???????? ?????? ?? ??????????? Baku - Antalya",
      "flight_price": "128.50 USD",
      "origin_name": "Baku",
      "destination_name": "Antalya",
      "feed_start_date": "01.11.2025",
      "final_url": "https://www.azal.az/az?utm_source=sheet_cataloue&from=BAK&to=AYT",
      "image_url": "https://raw.githubusercontent.com/subhanahmet/testflight/main/images/no_price/BAK-AYT.jpg?ts=621415",
      "github_image_urls": "https://raw.githubusercontent.com/subhanahmet/testflight/main/images/no_price/BAK-AYT.jpg",
      "feed_type": "Local Feed",
      "or_cirty": "",
      "dep_city": "",
      "flight_description": "",
      "rounded_price": 129
    },
    {
      "destination_id": "DXB",
      "origin_id": "BAK",
      "feed_description": "???????? ?????? ?? ??????????? Baku - Dubai",
      "flight_price": "165.90 USD",
      "origin_name": "Baku",
      "destination_name": "Dubai",
      "feed_start_date": "14.01.2026",
      "final_url": "https://www.azal.az/az?utm_source=sheet_cataloue&from=BAK&to=DXB",
      "image_url": "https://raw.githubusercontent.com/subhanahmet/testflight/main/images/no_price/BAK-DXB.jpg?ts=372582",
      "github_image_urls": "https://raw.githubusercontent.com/subhanahmet/testflight/main/images/no_price/BAK-DXB.jpg",
      "feed_type": "Local Feed",
      "or_cirty": "",
      "dep_city": "",
      "flight_description": "",
      "rounded_price": 166
    },
    {
      "destination_id": "BER",
      "origin_id": "BAK",
      "feed_description": "???????? ?????? ?? ??????????? Baku - Berlin",
      "flight_price": "190.00 USD",
      "origin_name": "Baku",
      "destination_name": "Berlin",
      "feed_start_date": "18.11.2025",
      "final_url": "https://www.azal.az/az?utm_source=sheet_cataloue&from=BAK&to=BER",
      "image_url": "https://raw.githubusercontent.com/subhanahmet/testflight/main/images/no_price/BAK-BER.jpg?ts=828071",
      "github_image_urls": "https://raw.githubusercontent.com/subhanahmet/testflight/main/images/no_price/BAK-BER.jpg",
      "feed_type": "Local Feed",
      "or_cirty": "",
      "dep_city": "",
      "flight_description": "",
      "rounded_price": 190
    },
    {
      "destination_id": "TBS",
      "origin_id": "BAK",
      "feed_description": "???????? ?????? ?? ??????????? Baku - Tbilisi",
      "flight_price": "61.50 USD",
      "origin_name": "Baku",
      "destination_name": "Tbilisi",
      "feed_start_date": "22.10.2025",
      "final_url": "https://www.azal.az/az?utm_source=sheet_cataloue&from=BAK&to=TBS",
      "image_url": "https://raw.githubusercontent.com/subhanahmet/testflight/main/images/no_price/BAK-TBS.jpg?ts=829486",
      "github_image_urls": "https://raw.githubusercontent.com/subhanahmet/testflight/main/images/no_price/BAK-TBS.jpg",
      "feed_type": "Local Feed",
      "or_cirty": "",
      "dep_city": "",
      "flight_description": "",
      "rounded_price": 62
    },
    {
      "destination_id": "MIL",
      "origin_id": "BAK",
      "feed_description": "???????? ?????? ?? ??????????? Baku - Milan",
      "flight_price": "197.20 USD",
      "origin_name": "Baku",
      "destination_name": "Milan",
      "feed_start_date": "06.11.2025",
      "final_url": "https://www.azal.az/az?utm_source=sheet_cataloue&from=BAK&to=MIL",
      "image_url": "https://raw.githubusercontent.com/subhanahmet/testflight/main/images/no_price/BAK-MIL.jpg?ts=687903",
      "github_image_urls": "https://raw.githubusercontent.com/subhanahmet/testflight/main/images/no_price/BAK-MIL.jpg",
      "feed_type": "Local Feed",
      "or_cirty": "",
      "dep_city": "",
      "flight_description": "",
      "rounded_price": 197
    },
    {
      "destination_id": "IZM",
      "origin_id": "BAK",
      "feed_description": "???????? ?????? ?? ??????????? Baku - Izmir",
      "flight_price": "76.20 USD",
      "origin_name": "Baku",
      "destination_name": "Izmir",
      "feed_start_date": "14.11.2025",
      "final_url": "https://www.azal.az/az?utm_source=sheet_cataloue&from=BAK&to=IZM",
      "image_url": "https://raw.githubusercontent.com/subhanahmet/testflight/main/images/no_price/BAK-IZM.jpg?ts=392721",
      "github_image_urls": "https://raw.githubusercontent.com/subhanahmet/testflight/main/images/no_price/BAK-IZM.jpg",
      "feed_type": "Local Feed",
      "or_cirty": "",
      "dep_city": "",
      "flight_description": "",
      "rounded_price": 76
    },
    {
      "destination_id": "PRG",
      "origin_id": "BAK",
      "feed_description": "???????? ?????? ?? ??????????? Baku - Prague",
      "flight_price": "182.20 USD",
      "origin_name": "Baku",
      "destination_name": "Prague",
      "feed_start_date": "14.11.2025",
      "final_url": "https://www.azal.az/az?utm_source=sheet_cataloue&from=BAK&to=PRG",
      "image_url": "https://raw.githubusercontent.com/subhanahmet/testflight/main/images/no_price/BAK-PRG.jpg?ts=521547",
      "github_image_urls": "https://raw.githubusercontent.com/subhanahmet/testflight/main/images/no_price/BAK-PRG.jpg",
      "feed_type": "Local Feed",
      "or_cirty": "",
      "dep_city": "",
      "flight_description": "",
      "rounded_price": 182
    },
    {
      "destination_id": "ANK",
      "origin_id": "BAK",
      "feed_description": "???????? ?????? ?? ??????????? Baku - Ankara",
      "flight_price": "63.50 USD",
      "origin_name": "Baku",
      "destination_name": "Ankara",
      "feed_start_date": "04.11.2025",
      "final_url": "https://www.azal.az/az?utm_source=sheet_cataloue&from=BAK&to=ANK",
      "image_url": "https://raw.githubusercontent.com/subhanahmet/testflight/main/images/no_price/BAK-ANK.jpg?ts=282445",
      "github_image_urls": "https://raw.githubusercontent.com/subhanahmet/testflight/main/images/no_price/BAK-ANK.jpg",
      "feed_type": "Local Feed",
      "or_cirty": "",
      "dep_city": "",
      "flight_description": "",
      "rounded_price": 64
    },
    {
      "destination_id": "ALA",
      "origin_id": "BAK",
      "feed_description": "???????? ?????? ?? ??????????? Baku - Almaty",
      "flight_price": "178.10 USD",
      "origin_name": "Baku",
      "destination_name": "Almaty",
      "feed_start_date": "04.11.2025",
      "final_url": "https://www.azal.az/az?utm_source=sheet_cataloue&from=BAK&to=ALA",
      "image_url": "https://raw.githubusercontent.com/subhanahmet/testflight/main/images/no_price/BAK-ALA.jpg?ts=115256",
      "github_image_urls": "https://raw.githubusercontent.com/subhanahmet/testflight/main/images/no_price/BAK-ALA.jpg",
      "feed_type": "Local Feed",
      "or_cirty": "",
      "dep_city": "",
      "flight_description": "",
      "rounded_price": 178
    },
    {
      "destination_id": "NQZ",
      "origin_id": "BAK",
      "feed_description": "???????? ?????? ?? ??????????? Baku - Astana",
      "flight_price": "120.10 USD",
      "origin_name": "Baku",
      "destination_name": "Astana",
      "feed_start_date": "13.01.2026",
      "final_url": "https://www.azal.az/az?utm_source=sheet_cataloue&from=BAK&to=NQZ",
      "image_url": "https://raw.githubusercontent.com/subhanahmet/testflight/main/images/no_price/BAK-NQZ.jpg?ts=694961",
      "github_image_urls": "https://raw.githubusercontent.com/subhanahmet/testflight/main/images/no_price/BAK-NQZ.jpg",
      "feed_type": "Local Feed",
      "or_cirty": "",
      "dep_city": "",
      "flight_description": "",
      "rounded_price": 120
    },
    {
      "destination_id": "IST",
      "origin_id": "BAK",
      "feed_description": "???????? ?????? ?? ??????????? Baku - Istanbul",
      "flight_price": "73.50 USD",
      "origin_name": "Baku",
      "destination_name": "Istanbul",
      "feed_start_date": "29.11.2025",
      "final_url": "https://www.azal.az/az?utm_source=sheet_cataloue&from=BAK&to=IST",
      "image_url": "https://raw.githubusercontent.com/subhanahmet/testflight/main/images/no_price/BAK-IST.jpg?ts=648897",
      "github_image_urls": "https://raw.githubusercontent.com/subhanahmet/testflight/main/images/no_price/BAK-IST.jpg",
      "feed_type": "Local Feed",
      "or_cirty": "",
      "dep_city": "",
      "flight_description": "",
      "rounded_price": 74
    },
    {
      "destination_id": "TZX",
      "origin_id": "BAK",
      "feed_description": "???????? ?????? ?? ??????????? Baku - Trabzon",
      "flight_price": "97.50 USD",
      "origin_name": "Baku",
      "destination_name": "Trabzon",
      "feed_start_date": "10.11.2025",
      "final_url": "https://www.azal.az/az?utm_source=sheet_cataloue&from=BAK&to=TZX",
      "image_url": "https://raw.githubusercontent.com/subhanahmet/testflight/main/images/no_price/BAK-TZX.jpg?ts=814616",
      "github_image_urls": "https://raw.githubusercontent.com/subhanahmet/testflight/main/images/no_price/BAK-TZX.jpg",
      "feed_type": "Local Feed",
      "or_cirty": "",
      "dep_city": "",
      "flight_description": "",
      "rounded_price": 98
    },
    {
      "destination_id": "VIE",
      "origin_id": "BAK",
      "feed_description": "???????? ?????? ?? ??????????? Baku - Vienna",
      "flight_price": "189.30 USD",
      "origin_name": "Baku",
      "destination_name": "Vienna",
      "feed_start_date": "18.11.2025",
      "final_url": "https://www.azal.az/az?utm_source=sheet_cataloue&from=BAK&to=VIE",
      "image_url": "https://raw.githubusercontent.com/subhanahmet/testflight/main/images/no_price/BAK-VIE.jpg?ts=587916",
      "github_image_urls": "https://raw.githubusercontent.com/subhanahmet/testflight/main/images/no_price/BAK-VIE.jpg",
      "feed_type": "Local Feed",
      "or_cirty": "",
      "dep_city": "",
      "flight_description": "",
      "rounded_price": 189
    },
    {
      "destination_id": "LED",
      "origin_id": "BAK",
      "feed_description": "???????? ?????? ?? ??????????? Baku - St Petersburg",
      "flight_price": "217.10 USD",
      "origin_name": "Baku",
      "destination_name": "St Petersburg",
      "feed_start_date": "05.12.2025",
      "final_url": "https://www.azal.az/az?utm_source=sheet_cataloue&from=BAK&to=LED",
      "image_url": "https://raw.githubusercontent.com/subhanahmet/testflight/main/images/no_price/BAK-LED.jpg?ts=934065",
      "github_image_urls": "https://raw.githubusercontent.com/subhanahmet/testflight/main/images/no_price/BAK-LED.jpg",
      "feed_type": "Local Feed",
      "or_cirty": "",
      "dep_city": "",
      "flight_description": "",
      "rounded_price": 217
    }
  ]
}